xcae/__init__.py
xcae/__main__.py
xcae/constraints.py
xcae/context.py
xcae/elements.py
xcae/instance.py
xcae/job.py
xcae/model.py
xcae/parser.py
xcae/part.py
xcae-0.0.1.dist-info/METADATA
xcae-0.0.1.dist-info/WHEEL
xcae-0.0.1.dist-info/entry_points.txt
xcae-0.0.1.dist-info/top_level.txt
xcae-0.0.1.dist-info/RECORD
