Metadata-Version: 2.4
Name: xcae
Version: 0.0.1
Summary: Read finite element models from Abaqus and perform simulations with xara.
Author-email: Issac Pang <101420268+issacpang@users.noreply.github.com>
License-Expression: MIT AND (Apache-2.0 OR BSD-2-Clause)
Project-URL: Repository, https://github.com/STAIRLab/xara_abaqus
Project-URL: Home, https://gallery.stairlab.io
Keywords: dynamics,finite-element-analysis
Classifier: Development Status :: 5 - Production/Stable
Classifier: Intended Audience :: Science/Research
Classifier: Intended Audience :: Developers
Classifier: Programming Language :: C
Classifier: Programming Language :: Python
Classifier: Programming Language :: Python :: 3
Classifier: Programming Language :: Python :: 3.7
Classifier: Programming Language :: Python :: 3.8
Classifier: Programming Language :: Python :: 3.9
Classifier: Programming Language :: Python :: 3.10
Classifier: Programming Language :: Python :: 3.11
Classifier: Programming Language :: Python :: 3.12
Classifier: Programming Language :: Python :: 3 :: Only
Classifier: Programming Language :: Python :: Implementation :: CPython
Classifier: Topic :: Software Development
Classifier: Topic :: Scientific/Engineering
Classifier: Operating System :: Microsoft :: Windows
Classifier: Operating System :: POSIX
Classifier: Operating System :: Unix
Classifier: Operating System :: MacOS
Requires-Dist: xara
Requires-Dist: veux
Requires-Dist: meshio
Requires-Dist: numpy
Requires-Dist: openbim
